dashpaan/__init__.py
django/__init__.py
elements/__init__.py
elements/base.py
elements/button.py
elements/card.py
elements/chart_comparison.py
elements/circular_distribution.py
elements/data_table.py
elements/donut_chart.py
elements/flex.py
elements/form.py
elements/form_element_upload_image.py
elements/heading.py
elements/information.py
elements/line_chart.py
elements/navigation.py
elements/page.py
elements/pie_chart.py
elements/qr_code.py
elements/reverse.py
elements/select.py
elements/sticky_stat.py
elements/sticky_target.py
elements/switch.py
elements/tabular.py
elements/text_area_editor.py
elements/text_field.py
elements/wave_chart.py
elements/wysiwig_editor.py
flask/__init__.py
json/__init__.py
dashpaan-1.0.4.dist-info/METADATA
dashpaan-1.0.4.dist-info/WHEEL
dashpaan-1.0.4.dist-info/top_level.txt
dashpaan-1.0.4.dist-info/RECORD
