Metadata-Version: 2.2
Name: dashpaan
Version: 1.0.4
Summary: Dashpaan is a Python package designed for creating dynamic dashboards and web pages with minimal code. It provides a wide range of UI components (elements) that can be easily integrated into web applications.
Home-page: https://github.com/monirs/dashpaan
Author: Monirs.co
Author-email: connect@monirs.com
Classifier: Programming Language :: Python :: 3
Classifier: License :: OSI Approved :: MIT License
Classifier: Operating System :: OS Independent
Requires-Python: >=3.6
Requires-Dist: jdatetime
Requires-Dist: traceback-with-variables
Dynamic: author
Dynamic: author-email
Dynamic: classifier
Dynamic: description
Dynamic: description-content-type
Dynamic: home-page
Dynamic: requires-dist
Dynamic: requires-python
Dynamic: summary
